csv_batch/__init__.py
csv_batch/read.py
csv_batch-0.3.0.dist-info/LICENSE
csv_batch-0.3.0.dist-info/METADATA
csv_batch-0.3.0.dist-info/WHEEL
csv_batch-0.3.0.dist-info/top_level.txt
csv_batch-0.3.0.dist-info/RECORD
