Metadata-Version: 2.1
Name: csv-batch
Version: 0.3.0
Summary: A Python Encryption Helper Library
Home-page: https://github.com/mitchelllisle/csv_batch
Author: Mitchell Lisle
Author-email: m.lisle90@gmail.com
License: UNKNOWN
Platform: UNKNOWN
